coapcpv/__init__.py
coapcpv/blockwise.py
coapcpv/credentials.py
coapcpv/defaults.py
coapcpv/error.py
coapcpv/interfaces.py
coapcpv/message.py
coapcpv/messagemanager.py
coapcpv/meta.py
coapcpv/options.py
coapcpv/optiontypes.py
coapcpv/oscore.py
coapcpv/oscore_sitewrapper.py
coapcpv/pipe.py
coapcpv/protocol.py
coapcpv/resource.py
coapcpv/tokenmanager.py
coapcpv/cli/__init__.py
coapcpv/cli/client.py
coapcpv/cli/common.py
coapcpv/cli/defaults.py
coapcpv/cli/fileserver.py
coapcpv/cli/proxy.py
coapcpv/cli/rd.py
coapcpv/numbers/__init__.py
coapcpv/numbers/codes.py
coapcpv/numbers/constants.py
coapcpv/numbers/contentformat.py
coapcpv/numbers/optionnumbers.py
coapcpv/numbers/types.py
coapcpv/proxy/__init__.py
coapcpv/proxy/client.py
coapcpv/proxy/server.py
coapcpv/resourcedirectory/__init__.py
coapcpv/resourcedirectory/client/__init__.py
coapcpv/resourcedirectory/client/register.py
coapcpv/transports/__init__.py
coapcpv/transports/generic_udp.py
coapcpv/transports/oscore.py
coapcpv/transports/rfc8323common.py
coapcpv/transports/simple6.py
coapcpv/transports/simplesocketserver.py
coapcpv/transports/tcp.py
coapcpv/transports/tinydtls.py
coapcpv/transports/tinydtls_server.py
coapcpv/transports/tls.py
coapcpv/transports/udp6.py
coapcpv/transports/ws.py
coapcpv/util/__init__.py
coapcpv/util/cli.py
coapcpv/util/contenttype.py
coapcpv/util/cryptography_additions.py
coapcpv/util/linkformat.py
coapcpv/util/linkformat_pygments.py
coapcpv/util/prettyprint.py
coapcpv/util/pyodide_websockets.py
coapcpv/util/socknumbers.py
coapcpv/util/uri.py
coapcpv/util/asyncio/__init__.py
coapcpv/util/asyncio/getaddrinfo_addrconfig.py
coapcpv/util/asyncio/recvmsg.py
coapcpv/util/asyncio/timeoutdict.py
coapcpv/util/vendored/link_header.py
coapcpv-0.0.6.dist-info/LICENSE
coapcpv-0.0.6.dist-info/METADATA
coapcpv-0.0.6.dist-info/WHEEL
coapcpv-0.0.6.dist-info/top_level.txt
coapcpv-0.0.6.dist-info/RECORD
