Metadata-Version: 2.1
Name: coapcpv
Version: 0.0.6
Summary: Python aiocoap dialect: CoAP Change Protocol Version 
Author-email: Erik Gonzalez <erikglez_ipn@hotmail.com>
License: MIT
Project-URL: Homepage, https://github.com/ErikGlz/coapcpv
Keywords: coap,asyncio,iot
Classifier: Framework :: AsyncIO
Classifier: Intended Audience :: Developers
Classifier: License :: OSI Approved :: MIT License
Classifier: Operating System :: OS Independent
Classifier: Programming Language :: Python
Classifier: Programming Language :: Python :: 3
Classifier: Topic :: Internet
Classifier: Topic :: Security
Classifier: Topic :: Software Development :: Libraries :: Python Modules
Classifier: Topic :: System :: Networking
Requires-Python: >=3.7
License-File: LICENSE
